rpa_executor_icodefun/__init__.py
rpa_executor_icodefun/config.py
rpa_executor_icodefun/gunicorn.conf.py
rpa_executor_icodefun/robot_keywords.py
rpa_executor_icodefun/run.py
rpa_executor_icodefun/task_io.py
rpa_executor_icodefun/tasks.py
rpa_executor_icodefun/xxl_biz_api.py
rpa_executor_icodefun/templates/config.yaml.template
rpa_executor_icodefun/templates/manifest.yaml.template
rpa_executor_icodefun-1.6.4.dist-info/METADATA
rpa_executor_icodefun-1.6.4.dist-info/WHEEL
rpa_executor_icodefun-1.6.4.dist-info/entry_points.txt
rpa_executor_icodefun-1.6.4.dist-info/licenses/LICENSE
rpa_executor_icodefun-1.6.4.dist-info/RECORD
